tradingview_defi_strategy/__init__.py
tradingview_defi_strategy/trader_joe_grid_search.py
tradingview_defi_strategy/uniswap_grid_search.py
tradingview_defi_strategy-0.2.0.dist-info/METADATA
tradingview_defi_strategy-0.2.0.dist-info/WHEEL
tradingview_defi_strategy-0.2.0.dist-info/RECORD
