Metadata-Version: 2.1
Name: tradingview-defi-strategy
Version: 0.2.0
Summary: Convert TradingView and PineScript based algorithmig trading strategies for DeFi. An example repository.
Home-page: https://tradingstrategy.ai
License: MIT
Keywords: algorithmic trading,ethereum,cryptocurrency,tradingview,quantitative finance,binance,coinbase,uniswap
Author: Mikko Ohtamaa
Author-email: mikko@opensourcehacker.com
Requires-Python: >=3.10,<3.11
Classifier: License :: OSI Approved :: MIT License
Classifier: Programming Language :: Python :: 3
Classifier: Programming Language :: Python :: 3.10
Requires-Dist: ipdb (>=0.13.13,<0.14.0)
Requires-Dist: ipython (>=8.12.0,<9.0.0)
Requires-Dist: pytest (>=7.3.0,<8.0.0)
Requires-Dist: trade-executor[data,execution,quantstats,web-server] (==0.3)
Project-URL: Repository, https://github.com/tradingstrategy-ai/tradingview-defi-strategy
